pyrorouter/__init__.py
pyrorouter/client.py
pyrorouter/router.py
pyrorouter-0.1.2.dist-info/LICENSE
pyrorouter-0.1.2.dist-info/METADATA
pyrorouter-0.1.2.dist-info/WHEEL
pyrorouter-0.1.2.dist-info/RECORD
