Metadata-Version: 2.1
Name: pyrorouter
Version: 0.1.2
Summary: A simple router for Pyrogram
License: LGPLv3
Keywords: router,pyrogram
Author: Łukasz Tshipenchko
Author-email: dev@zxc.sx
Requires-Python: >=3.7,<4.0
Classifier: License :: Other/Proprietary License
Classifier: Programming Language :: Python :: 3
Classifier: Programming Language :: Python :: 3.7
Classifier: Programming Language :: Python :: 3.8
Classifier: Programming Language :: Python :: 3.9
Classifier: Programming Language :: Python :: 3.10
Classifier: Programming Language :: Python :: 3.11
Requires-Dist: pyrogram (>=2.0.106,<3.0.0)
